{"format":2,"version":"5.5","globals":"38c562db668a4c95c907bca7a3be0717","files":{"crm_api_decorators_py":{"hash":"d60c2462767e044fdd431d5fc0475454","index":{"nums":[1,9,0,0,0,0,0],"html_filename":"crm_api_decorators_py.html","relative_filename":"crm_api/decorators.py"}},"crm_api_filters_py":{"hash":"97d6f2f4e549a05b8c277dc45585f229","index":{"nums":[1,79,0,3,0,0,0],"html_filename":"crm_api_filters_py.html","relative_filename":"crm_api/filters.py"}},"crm_api_permissions_py":{"hash":"7ba340eb6eab38e5e1ad0d483b5ea090","index":{"nums":[1,24,0,4,0,0,0],"html_filename":"crm_api_permissions_py.html","relative_filename":"crm_api/permissions.py"}},"crm_api_tests___init___py":{"hash":"af9d0d0de0ea3b71d198bc63f1499a7d","index":{"nums":[1,0,0,0,0,0,0],"html_filename":"crm_api_tests___init___py.html","relative_filename":"crm_api/tests/__init__.py"}},"crm_api_tests_test_filters_py":{"hash":"4a3d07104fb46c71002c087a611bf6de","index":{"nums":[1,50,0,0,0,0,0],"html_filename":"crm_api_tests_test_filters_py.html","relative_filename":"crm_api/tests/test_filters.py"}},"crm_api_tests_test_models_py":{"hash":"770b4c85587331a493e20cfd42e31139","index":{"nums":[1,152,0,0,0,0,0],"html_filename":"crm_api_tests_test_models_py.html","relative_filename":"crm_api/tests/test_models.py"}},"crm_api_tests_test_serializers_py":{"hash":"656f51642805cb03878fd6d294cabd61","index":{"nums":[1,184,0,0,0,0,0],"html_filename":"crm_api_tests_test_serializers_py.html","relative_filename":"crm_api/tests/test_serializers.py"}},"crm_api_tests_test_views_py":{"hash":"433631cb6a59244b0f19ec206ddb58e0","index":{"nums":[1,389,0,0,0,0,0],"html_filename":"crm_api_tests_test_views_py.html","relative_filename":"crm_api/tests/test_views.py"}},"crm_api_views_py":{"hash":"0be21478e1e2bbff534a712c84190031","index":{"nums":[1,266,0,20,0,0,0],"html_filename":"crm_api_views_py.html","relative_filename":"crm_api/views.py"}},"crm_api_models_py":{"hash":"7bc3fc663ad7cd08bb4661f278a89f06","index":{"nums":[1,74,0,0,0,0,0],"html_filename":"crm_api_models_py.html","relative_filename":"crm_api/models.py"}},"crm_api_serializers_py":{"hash":"b2deff9657e4d78de2bc31db95958e91","index":{"nums":[1,114,0,4,0,0,0],"html_filename":"crm_api_serializers_py.html","relative_filename":"crm_api/serializers.py"}}}}